gabits/__init__.py
gabits/ga.py
gabits/utilities.py
gabits-1.0.0.1.dist-info/METADATA
gabits-1.0.0.1.dist-info/WHEEL
gabits-1.0.0.1.dist-info/top_level.txt
gabits-1.0.0.1.dist-info/RECORD
