Metadata-Version: 2.2
Name: gabits
Version: 1.0.0.1
Summary: Genetic algorithm implementation based on binary representation
Home-page: https://github.com/diogomachado-bioinfo/gabits
Author: Diogo de J. S. Machado
Author-email: diogomachado.bioinfo@gmail.com
Requires-Dist: numpy
Dynamic: author
Dynamic: author-email
Dynamic: description
Dynamic: description-content-type
Dynamic: home-page
Dynamic: requires-dist
Dynamic: summary
